query_search/__init__.py
query_search/cli.py
query_search/q.py
query_search-0.0.2.dist-info/licenses/LICENSE
query_search-0.0.2.dist-info/METADATA
query_search-0.0.2.dist-info/WHEEL
query_search-0.0.2.dist-info/entry_points.txt
query_search-0.0.2.dist-info/top_level.txt
query_search-0.0.2.dist-info/RECORD
