Metadata-Version: 2.4
Name: query-search
Version: 0.0.2
Summary: A package to filter pipe outputs or text files like `grep` using sql syntax
Home-page: 
Author: Daniel Olson
Author-email: daniel@orphos.cloud
Keywords: terminal query search grep sql
Classifier: Development Status :: 3 - Alpha
Classifier: Intended Audience :: Developers
Classifier: License :: OSI Approved :: MIT License
Classifier: Operating System :: OS Independent
Classifier: Programming Language :: Python :: 3
Classifier: Programming Language :: Python :: 3.10
Classifier: Programming Language :: Python :: 3.11
Classifier: Programming Language :: Python :: 3.12
Requires-Python: >=3.10
License-File: LICENSE
Dynamic: author
Dynamic: author-email
Dynamic: classifier
Dynamic: description
Dynamic: description-content-type
Dynamic: keywords
Dynamic: license-file
Dynamic: requires-python
Dynamic: summary
